LICENSE
nore/__init__.py
nore/list.py
nore/main.py
nore/new.py
nore/util.py
nore-0.1.1.dist-info/entry_points.txt
nore-0.1.1.dist-info/LICENSE
nore-0.1.1.dist-info/WHEEL
nore-0.1.1.dist-info/METADATA
nore-0.1.1.dist-info/RECORD
