Metadata-Version: 2.1
Name: nore
Version: 0.1.1
Summary: Download .gitignore files from the github/gitignore repo.
Home-page: https://github.com/tcoliver/nore
License: MIT
Keywords: git,.gitignore,VCS
Author: Trenten Oliver
Author-email: trentenoliver@outlook.com
Requires-Python: >=3.9,<4.0
Classifier: Development Status :: 4 - Beta
Classifier: Environment :: Console
Classifier: Intended Audience :: Developers
Classifier: License :: OSI Approved :: MIT License
Classifier: Operating System :: MacOS
Classifier: Operating System :: Microsoft :: Windows
Classifier: Operating System :: POSIX :: Linux
Classifier: Programming Language :: Python :: 3
Classifier: Programming Language :: Python :: 3.9
Classifier: Topic :: Software Development
Classifier: Topic :: Software Development :: Version Control
Classifier: Topic :: Utilities
Requires-Dist: click (>=8.0.1,<9.0.0)
Requires-Dist: pydantic (>=1.8.2,<2.0.0)
Project-URL: Repository, https://github.com/tcoliver/nore
